abap_adt_py/__init__.py
abap_adt_py/adt_client.py
abap_adt_py/compat_typing.py
abap_adt_py/http_request.py
abap_adt_py/response_parsing.py
abap_adt_py/api/__init__.py
abap_adt_py/api/activate.py
abap_adt_py/api/content.py
abap_adt_py/api/create.py
abap_adt_py/api/delete.py
abap_adt_py/api/lock.py
abap_adt_py/api/login.py
abap_adt_py/api/objectstructure.py
abap_adt_py/api/prettyprint.py
abap_adt_py/api/search.py
abap_adt_py/api/syntax.py
abap_adt_py/api/unittest.py
abap_adt_py/api/xml_namespaces.py
abap_adt_py-0.1.4.dist-info/licenses/LICENSE
abap_adt_py-0.1.4.dist-info/METADATA
abap_adt_py-0.1.4.dist-info/WHEEL
abap_adt_py-0.1.4.dist-info/top_level.txt
abap_adt_py-0.1.4.dist-info/RECORD
