Metadata-Version: 2.4
Name: abap-adt-py
Version: 0.1.4
Summary: A Python library for interacting with SAP systems using the ADT (ABAP Development Tools) protocol.
Author-email: Tim Köhne <20153452+timkoehne@users.noreply.github.com>
License-Expression: MIT
Project-URL: Homepage, https://github.com/timkoehne/abap-adt-py
Project-URL: Bug Tracker, https://github.com/timkoehne/abap-adt-py/issues
Classifier: Programming Language :: Python :: 3
Classifier: Programming Language :: Python :: 3.7
Classifier: Operating System :: OS Independent
Requires-Python: >=3.7
License-File: LICENSE
Requires-Dist: requests>=2.25
Requires-Dist: typing-extensions>=4.7.1
Dynamic: license-file
